alang/__init__.py
alang/compiler.py
alang/exprs.py
alang/funcs.py
alang/nodes.py
alang/stmts.py
alang/typs.py
alang/vals.py
alang/langs/__init__.py
alang/langs/a.py
alang/langs/a.y
alang/langs/a_parser.py
alang/langs/c.py
alang/langs/glsl.py
alang/langs/html_dev.py
alang/langs/js.py
alang/langs/language.py
alang/langs/metal.py
alang/langs/py.skel
alang/langs/wgsl.py
alang/langs/writer.py
alang-0.0.4.dist-info/METADATA
alang-0.0.4.dist-info/WHEEL
alang-0.0.4.dist-info/licenses/LICENSE
alang-0.0.4.dist-info/RECORD
